config_engine/__init__.py
config_engine/settings.py
config_engine/wsgi.py
config_engine/base/__init__.py
config_engine/base/file_storage.py
config_engine/base/filters.py
config_engine/base/models.py
config_engine/base/urls.py
config_engine/base/utils.py
config_engine/payer_source_system/__init__.py
config_engine/payer_source_system/admin.py
config_engine/payer_source_system/filters.py
config_engine/payer_source_system/models.py
config_engine/payer_source_system/serializers.py
config_engine/payer_source_system/urls.py
config_engine/payer_source_system/views.py
config_engine/payer_source_system/migrations/0001_initial.py
config_engine/payer_source_system/migrations/__init__.py
config_engine/rule_sets/__init__.py
config_engine/rule_sets/models.py
config_engine/rule_sets/migrations/0001_initial.py
config_engine/rule_sets/migrations/__init__.py
config_engine/semantic_key_registry/__init__.py
config_engine/semantic_key_registry/admin.py
config_engine/semantic_key_registry/models.py
config_engine/semantic_key_registry/urls.py
config_engine/semantic_key_registry/views.py
config_engine/semantic_key_registry/migrations/0001_initial.py
config_engine/semantic_key_registry/migrations/__init__.py
test/unit/__init__.py
test/unit/client.py
test/unit/test_settings.py
test/unit/payer_source_system/__init__.py
test/unit/payer_source_system/test_views.py
config_engine-0.0.129.dist-info/LICENSE
config_engine-0.0.129.dist-info/METADATA
config_engine-0.0.129.dist-info/WHEEL
config_engine-0.0.129.dist-info/top_level.txt
config_engine-0.0.129.dist-info/RECORD
