Metadata-Version: 2.1
Name: config-engine
Version: 0.0.129
Summary: Zipari Config Engine
Home-page: http://gitlab.zipari.net/cx/config-engine/
Author: Zipari
Author-email: UNKNOWN
License: UNKNOWN
Platform: UNKNOWN
Requires-Dist: boto3 (==1.7.4)
Requires-Dist: Django (==2.0.3)
Requires-Dist: django-cors-headers (==2.1.0)
Requires-Dist: djangorestframework (==3.7.7)
Requires-Dist: djangorestframework-csv (==2.1.0)
Requires-Dist: django-filter (==1.1.0)
Requires-Dist: django-redis (==4.8.0)
Requires-Dist: django-storages (==1.6.5)
Requires-Dist: django-celery-results (==1.0.1)
Requires-Dist: psycopg2 (==2.7.3.2)
Requires-Dist: Faker (==0.8.7)
Requires-Dist: fdfgen (==0.16.0)
Requires-Dist: openpyxl (==2.5.3)
Requires-Dist: PyYAML (==3.12)
Requires-Dist: raven (==6.7.0)
Requires-Dist: redis-py-cluster (==1.3.4)
Requires-Dist: pika (>=0.12.0)
Requires-Dist: celery (>=4.1.0)
Requires-Dist: flower (==0.9.2)
Requires-Dist: django-rest-swagger (>=2.0.0)
Requires-Dist: drf-yasg (==1.11.0)
Requires-Dist: rx (==1.6.1)
Requires-Dist: django-simple-history (==2.7.0)
